worldfinder/__init__.py
worldfinder/_internals.py
worldfinder/check_city.py
worldfinder/data/cities.csv
worldfinder/data/countries.csv
worldfinder/get_capital.py
worldfinder/get_countries.py
worldfinder/get_country_statistic.py
worldfinder-1.0.0.dist-info/LICENSE
worldfinder-1.0.0.dist-info/METADATA
worldfinder-1.0.0.dist-info/WHEEL
worldfinder-1.0.0.dist-info/RECORD
