Metadata-Version: 2.3
Name: worldfinder
Version: 1.0.0
Summary: This package will contain four functions that will perform actions related to cities and countries across the world.
License: MIT
Author: Group 17
Requires-Python: >=3.9,<4.0
Classifier: License :: OSI Approved :: MIT License
Classifier: Programming Language :: Python :: 3
Classifier: Programming Language :: Python :: 3.9
Classifier: Programming Language :: Python :: 3.10
Classifier: Programming Language :: Python :: 3.11
Classifier: Programming Language :: Python :: 3.12
Classifier: Programming Language :: Python :: 3.13
Requires-Dist: pandas (>=2.2.0,<3.0.0)
